pyaux/Colorer.py
pyaux/__init__.py
pyaux/_pylibnewrelease.py
pyaux/aio.py
pyaux/anyjson.py
pyaux/base.py
pyaux/dicts.py
pyaux/exc_ipdb.py
pyaux/exc_log.py
pyaux/iterables.py
pyaux/logging_annotators.py
pyaux/logging_helpers.py
pyaux/lzcat.py
pyaux/lzmah.py
pyaux/monkeys.py
pyaux/nb_highcharts.py
pyaux/net.py
pyaux/procs.py
pyaux/py.typed
pyaux/ranges.py
pyaux/req.py
pyaux/runlib.py
pyaux/sre_tools.py
pyaux/urlhelpers.py
pyaux/all/__init__.py
pyaux/bin/__init__.py
pyaux/bin/f_convert.py
pyaux/bin/fjson.py
pyaux/bin/fjson_yaml.py
pyaux/bin/fmsgp_json.py
pyaux/bin/fyaml_json.py
pyaux/bin/py_tcp_proxy.py
pyaux/bin/wittgendoc.py
pyaux/datadeque/__init__.py
pyaux/datadeque/_datadeque.pyx
pyaux/madness/__init__.py
pyaux/madness/datadiff.py
pyaux/madness/oneliny.py
pyaux/madness/reprstuff.py
pyaux/madness/stuffstuff.py
pyaux/prof/__init__.py
pyaux/prof/lp_helper.py
pyaux-4.0.0.dist-info/entry_points.txt
pyaux-4.0.0.dist-info/licenses/LICENSE
pyaux-4.0.0.dist-info/WHEEL
pyaux-4.0.0.dist-info/METADATA
pyaux-4.0.0.dist-info/RECORD
