Metadata-Version: 2.4
Name: pyaux
Version: 4.0.0
Summary: A collection of small useful helpers.
Author-email: HoverHell <hoverhell@gmail.com>
Requires-Python: >=3.11
Classifier: Development Status :: 6 - Mature
Classifier: Intended Audience :: Developers
Classifier: License :: OSI Approved :: MIT License
Classifier: Operating System :: OS Independent
Classifier: Programming Language :: Python
Classifier: Programming Language :: Python :: 3
Classifier: Programming Language :: Python :: 3.11
Classifier: Topic :: Software Development :: Libraries :: Python Modules
License-File: LICENSE
Requires-Dist: black ; extra == "dev"
Requires-Dist: isort ; extra == "dev"
Requires-Dist: Cython ; extra == "known"
Requires-Dist: django ; extra == "known"
Requires-Dist: line_profiler ; extra == "known"
Requires-Dist: pandas ; extra == "known"
Requires-Dist: Pygments ; extra == "known"
Requires-Dist: pylzma ; extra == "known"
Requires-Dist: build ; extra == "known"
Requires-Dist: twine ; extra == "known"
Requires-Dist: ipdb ; extra == "recommended"
Requires-Dist: ipython ; extra == "recommended"
Requires-Dist: orjson ; extra == "recommended"
Requires-Dist: PyYAML ; extra == "recommended"
Requires-Dist: toml ; extra == "recommended"
Requires-Dist: requests[ssl] ; extra == "req"
Requires-Dist: autoflake>=1.5.3 ; extra == "tests"
Requires-Dist: docutils>=0.19 ; extra == "tests"
Requires-Dist: flake8>=5.0.4 ; extra == "tests"
Requires-Dist: flake8-future-import>=0.4.7 ; extra == "tests"
Requires-Dist: flake8-print>=5.0.0 ; extra == "tests"
Requires-Dist: isort>=5.10.1 ; extra == "tests"
Requires-Dist: mock>=4.0.3 ; extra == "tests"
Requires-Dist: mypy>=0.990 ; extra == "tests"
Requires-Dist: pep8-naming>=0.13.2 ; extra == "tests"
Requires-Dist: Pygments>=2.13.0 ; extra == "tests"
Requires-Dist: pylint>=2.15.5 ; extra == "tests"
Requires-Dist: pyproject-flake8>=5.0.4.post1 ; extra == "tests"
Requires-Dist: pytest>=7.2.0 ; extra == "tests"
Requires-Dist: pytest-asyncio>=0.20.1 ; extra == "tests"
Requires-Dist: pytest-cov>=4.0.0 ; extra == "tests"
Requires-Dist: pytest-html>=3.2.0 ; extra == "tests"
Requires-Dist: requests>=2.28.1 ; extra == "tests"
Requires-Dist: tox>=3.27.0 ; extra == "tests"
Project-URL: Home, https://gitlab.com/hoverhell/pyaux
Provides-Extra: dev
Provides-Extra: known
Provides-Extra: recommended
Provides-Extra: req
Provides-Extra: tests
